[
{"hotel": "GAMBETTA r\u00e9sidences h\u00f4tel Paris centre", "url": "https://www.booking.com/hotel/fr/gambetta-rue-des-rondonneaux-75020-paris-centre.fr.html"},
{"hotel": "Sonder Quintinie", "url": "https://www.booking.com/hotel/fr/residence-quintinie-square.fr.html"},
{"hotel": "Best Western Bretagne Montparnasse", "url": "https://www.booking.com/hotel/fr/bwdebretagne.fr.html"},
{"hotel": "H\u00f4tel Sunny", "url": "https://www.booking.com/hotel/fr/sunny.fr.html"},
{"hotel": "H\u00f4tel Le Daum", "url": "https://www.booking.com/hotel/fr/gossec.fr.html"},
{"hotel": "Le Petit Cosy H\u00f4tel", "url": "https://www.booking.com/hotel/fr/cosy.fr.html"},
{"hotel": "ibis Paris Bastille Faubourg St Antoine", "url": "https://www.booking.com/hotel/fr/bastille-faubourg-st-antoine.fr.html"},
{"hotel": "H\u00f4tel Clauzel Paris", "url": "https://www.booking.com/hotel/fr/clauzel.fr.html"},
{"hotel": "Hotel Ariane Montparnasse by Patrick Hayat", "url": "https://www.booking.com/hotel/fr/ariane-montparnasse.fr.html"},
{"hotel": "H\u00f4tel Pavillon Bastille", "url": "https://www.booking.com/hotel/fr/pavillonbastille.fr.html"},
{"hotel": "Hilton Garden Inn Paris La Villette", "url": "https://www.booking.com/hotel/fr/hilton-garden-inn-paris-la-villette.fr.html"},
{"hotel": "ibis Styles Paris Bercy", "url": "https://www.booking.com/hotel/fr/mercure-paris-bercy.fr.html"},
{"hotel": "H\u00f4tel Magellan", "url": "https://www.booking.com/hotel/fr/ha-tel-magellan.fr.html"},
{"hotel": "ibis Paris Gare du Nord Ch\u00e2teau Landon 10\u00e8me", "url": "https://www.booking.com/hotel/fr/ibis-gare-du-nord-chateau-landon.fr.html"},
{"hotel": "Montparnasse Daguerre", "url": "https://www.booking.com/hotel/fr/hoteldaguerre.fr.html"},
{"hotel": "Le Hameau de Passy", "url": "https://www.booking.com/hotel/fr/lehameaudepassy.fr.html"},
{"hotel": "Motel One Paris-Porte Dor\u00e9e", "url": "https://www.booking.com/hotel/fr/motel-one-paris-porte-doree.fr.html"},
{"hotel": "Hotel Armoni Paris", "url": "https://www.booking.com/hotel/fr/armoni-paris.fr.html"},
{"hotel": "Appart'City Classic Paris La Villette", "url": "https://www.booking.com/hotel/fr/appart-city-cap-affaires-paris.fr.html"},
{"hotel": "voco Paris Montparnasse, an IHG Hotel", "url": "https://www.booking.com/hotel/fr/holiday-inn-paris-montparnasse-maine.fr.html"}
]